{"type":"Topology","transform":{"scale":[0.00001,0.000009999999999999999],"translate":[-63.15345,-21.38922]},"objects":{"NUTS":{"type":"GeometryCollection","geometries":[{"type":"Polygon","arcs":[[0,1,2,3,4,5,6]],"id":"HU322","properties":{"NUTS_ID":"HU322","LEVL_CODE":3,"CNTR_CODE":"HU","NUTS_NAME":"Jász-Nagykun-Szolnok","FID":"HU322"}},{"type":"Polygon","arcs":[[11]],"id":"HU101","properties":{"NUTS_ID":"HU101","LEVL_CODE":3,"CNTR_CODE":"HU","NUTS_NAME":"Budapest","FID":"HU101"}},{"type":"Polygon","arcs":[[15,16,17,18,-3,19,20],[-12]],"id":"HU102","properties":{"NUTS_ID":"HU102","LEVL_CODE":3,"CNTR_CODE":"HU","NUTS_NAME":"Pest","FID":"HU102"}},{"type":"Polygon","arcs":[[-8,-11,21,22,23,24,25,26]],"id":"HU221","properties":{"NUTS_ID":"HU221","LEVL_CODE":3,"CNTR_CODE":"HU","NUTS_NAME":"Győr-Moson-Sopron","FID":"HU221"}},{"type":"Polygon","arcs":[[-15,29,30,31,32,-10]],"id":"HU323","properties":{"NUTS_ID":"HU323","LEVL_CODE":3,"CNTR_CODE":"HU","NUTS_NAME":"Szabolcs-Szatmár-Bereg","FID":"HU323"}},{"type":"Polygon","arcs":[[33,34,35,36,37,-21]],"id":"HU211","properties":{"NUTS_ID":"HU211","LEVL_CODE":3,"CNTR_CODE":"HU","NUTS_NAME":"Fejér","FID":"HU211"}},{"type":"Polygon","arcs":[[38,-6,39,-30,-14]],"id":"HU321","properties":{"NUTS_ID":"HU321","LEVL_CODE":3,"CNTR_CODE":"HU","NUTS_NAME":"Hajdú-Bihar","FID":"HU321"}},{"type":"Polygon","arcs":[[-18,-28,-43,43,44]],"id":"HU313","properties":{"NUTS_ID":"HU313","LEVL_CODE":3,"CNTR_CODE":"HU","NUTS_NAME":"Nógrád","FID":"HU313"}},{"type":"Polygon","arcs":[[45,-25,-29,-16,-38]],"id":"HU212","properties":{"NUTS_ID":"HU212","LEVL_CODE":3,"CNTR_CODE":"HU","NUTS_NAME":"Komárom-Esztergom","FID":"HU212"}},{"type":"Polygon","arcs":[[-44,-42,-41,-31,-40,-5,46]],"id":"HU311","properties":{"NUTS_ID":"HU311","LEVL_CODE":3,"CNTR_CODE":"HU","NUTS_NAME":"Borsod-Abaúj-Zemplén","FID":"HU311"}},{"type":"Polygon","arcs":[[-45,-47,-4,-19]],"id":"HU312","properties":{"NUTS_ID":"HU312","LEVL_CODE":3,"CNTR_CODE":"HU","NUTS_NAME":"Heves","FID":"HU312"}},{"type":"Polygon","arcs":[[47,48,49,50,51]],"id":"HU231","properties":{"NUTS_ID":"HU231","LEVL_CODE":3,"CNTR_CODE":"HU","NUTS_NAME":"Baranya","FID":"HU231"}},{"type":"Polygon","arcs":[[55,56,57,-36,58,-49,-55]],"id":"HU232","properties":{"NUTS_ID":"HU232","LEVL_CODE":3,"CNTR_CODE":"HU","NUTS_NAME":"Somogy","FID":"HU232"}},{"type":"Polygon","arcs":[[-7,-39,-13,60,61]],"id":"HU332","properties":{"NUTS_ID":"HU332","LEVL_CODE":3,"CNTR_CODE":"HU","NUTS_NAME":"Békés","FID":"HU332"}},{"type":"Polygon","arcs":[[63,-50,-59,-35]],"id":"HU233","properties":{"NUTS_ID":"HU233","LEVL_CODE":3,"CNTR_CODE":"HU","NUTS_NAME":"Tolna","FID":"HU233"}},{"type":"Polygon","arcs":[[64,65,66,-1,-62,67]],"id":"HU333","properties":{"NUTS_ID":"HU333","LEVL_CODE":3,"CNTR_CODE":"HU","NUTS_NAME":"Csongrád","FID":"HU333"}},{"type":"Polygon","arcs":[[-37,-58,68,69,-26,-46]],"id":"HU213","properties":{"NUTS_ID":"HU213","LEVL_CODE":3,"CNTR_CODE":"HU","NUTS_NAME":"Veszprém","FID":"HU213"}},{"type":"Polygon","arcs":[[-9,-27,-70,70,-53,71]],"id":"HU222","properties":{"NUTS_ID":"HU222","LEVL_CODE":3,"CNTR_CODE":"HU","NUTS_NAME":"Vas","FID":"HU222"}},{"type":"Polygon","arcs":[[-60,-51,-64,-34,-20,-2,-67,72]],"id":"HU331","properties":{"NUTS_ID":"HU331","LEVL_CODE":3,"CNTR_CODE":"HU","NUTS_NAME":"Bács-Kiskun","FID":"HU331"}},{"type":"Polygon","arcs":[[-71,-69,-57,-63,-74,-54]],"id":"HU223","properties":{"NUTS_ID":"HU223","LEVL_CODE":3,"CNTR_CODE":"HU","NUTS_NAME":"Zala","FID":"HU223"}}]}},"arcs":[[[8357761,6819275],[43,-437],[-2047,-1082],[-5193,-364],[-602,-541],[-112,-1208],[-1254,-528],[-4190,557],[-2588,2475],[-3402,639],[-1234,-671],[-78,-393],[558,-260],[-542,-511],[-1867,314],[-2394,-2891],[-6437,3068],[-799,-352],[365,-1408],[-1573,-531],[77,1098],[-800,1283],[-1724,460],[-511,1572]],[[8321457,6819564],[-22,602],[-1701,1166],[-838,-81],[-439,-554],[938,-1311],[-393,-706],[-699,-114],[-2418,1422],[-351,1081],[3965,902],[156,641],[1819,388],[4195,-198],[1140,388],[-742,1258],[-1314,542],[-854,1380],[3645,2097],[196,1075],[2699,537],[894,880],[-217,856],[-1102,1101],[-2097,342],[-1868,-546],[-344,1397],[2724,751],[265,600],[-670,912],[1221,921],[-1419,1090],[-3025,1283]],[[8324801,6839666],[1808,2596],[-428,599],[-1652,440],[-1227,3256],[-1469,1399],[130,344],[-1175,1240],[420,247],[-171,355],[-975,1300],[869,2032],[2871,1932],[1430,1662],[-1398,2651],[-480,218],[-61,1025],[-4579,2239],[-4548,1026],[2931,5083],[-2555,2489],[-156,1784],[-2539,2060],[-4293,1548],[-9752,4612],[195,353],[-741,1203],[-1537,1530],[-5681,2924],[1687,1249],[611,1501],[2114,1604],[-1382,636],[-939,-849],[-1071,545],[-1106,-375],[-984,684],[-2550,-2049],[-804,-116],[-2039,1625],[-2965,1436],[591,1133],[-754,273],[1529,2665]],[[8281976,6897775],[1509,271],[2373,-690],[-314,2201],[3777,1316],[1810,165],[6074,-2725],[1758,1193],[833,1495],[2730,975],[-186,1242],[583,2456],[3563,-1310],[4941,1261],[1006,958],[2055,-304],[1224,-1398],[362,-3125],[1156,-1238],[-1359,-2210],[1430,-1392],[9254,-2663],[2219,1215],[-1842,773],[-1360,1662],[7074,1674],[3584,68],[514,-2449],[1086,-338],[644,-877],[-46,-868],[2892,-640],[-487,-781],[3117,-499],[1088,-1454],[563,-945],[-82,-951],[-1418,-2222],[354,-445],[4569,-4008],[2694,-166],[1603,541],[131,-916],[-472,-102],[439,-300],[-206,-803],[2151,-442],[2347,371],[1782,953],[690,660],[193,1223],[1911,1204],[1744,-186],[1832,691],[794,840],[803,2237],[5744,1440],[3089,2011],[5464,1725],[437,441],[-429,1387],[2309,-122],[1634,652],[490,1218],[-1063,434],[-165,580],[2079,901],[291,1478],[-458,1224],[1615,848],[2546,-169],[1459,1337]],[[8392502,6904358],[-682,1301],[3144,1509],[2296,-1216],[1129,-144],[-261,-996]],[[8398128,6904812],[-476,-1804],[1921,-4442],[1252,-147],[2797,-1308],[3286,347],[2981,1059],[2846,-1054],[2039,-1847],[204,-2853],[-353,-1140],[-888,-701],[861,-2329],[1538,-611],[-954,-610],[-470,-1143],[2564,-9422],[1069,-2284],[-1363,-10650],[-2453,-1725]],[[8414529,6862148],[-424,-658],[-1022,489],[-1008,-516],[-2210,-3894],[-1292,114],[-2280,-1459],[-1568,131],[-4628,-2608],[1275,-1466],[106,-1013],[669,-272],[-2332,-411],[282,-1677],[-363,-672],[795,-64],[-874,-1353],[1823,-1203],[-24,-415],[-480,-158],[34,343],[-1287,480],[-348,-982],[-3762,-1358],[843,-830],[-510,-103],[-4640,-95],[-345,1723],[-2853,-951],[-491,-1307],[-1504,463],[-557,-2267],[843,-35],[581,-663],[-715,-2735],[1099,-272],[-649,-213],[1294,-1202],[-279,-299],[-1176,433],[-808,-301],[691,-401],[1456,19],[196,-1011],[-702,-1398],[-2735,-2087],[-2061,312],[-3118,-1363],[-3449,1708],[-817,98],[-1620,-628],[-2922,506],[-708,-241],[-26,-788],[-849,-660],[-3970,-977],[-1996,311],[-1782,936],[-2713,-2852],[-2528,-1507],[1670,-5574]],[[7957605,6905502],[1780,-820],[4080,-700],[760,-820],[1080,-240],[900,-100],[760,760],[5740,-2600],[1700,-280],[4620,1020],[1720,-500],[680,-1640],[1360,-120],[-720,-840],[860,-1740],[-440,-820],[-720,-280],[820,-800],[1780,-80],[880,-1360],[1640,-600],[-1140,-640],[240,-1040],[-1060,-520],[-440,-720],[-2120,-700],[-640,540],[-1000,-840],[1780,-2640],[-1020,-1180],[160,-700],[-1671,-929]],[[7979974,6883573],[-1789,-411],[-720,-1140],[-860,100],[-800,-620],[-1580,-240],[120,-340],[-800,0],[140,-460],[-760,-280],[0,-620],[-5780,460],[-320,-580],[-540,0],[180,-780],[-1360,-800],[20,720],[-1300,160],[706,786],[-546,334],[-3040,340],[-940,-560],[1320,-2240],[-740,-540],[620,-1200],[-600,-980],[-1720,-460]],[[8533443,6898974],[898,1125],[1339,4310],[834,-91],[1047,821],[383,2582],[512,535],[2795,484],[328,1556],[-297,363],[526,1379],[2081,-179],[2072,1199],[1138,191],[338,1169],[-364,1099],[1311,-84],[2639,-1612],[5364,-232],[107,-427],[1877,-143],[-426,965],[2188,5248],[3354,783],[5846,-2895],[967,-936],[6198,-61],[519,552],[2992,153],[2410,916],[936,-49],[2133,2727],[-179,328],[976,566],[150,1052],[1186,389],[2915,-403],[1423,761],[1081,76],[-394,2039],[-1094,396],[640,1158],[-1021,739],[-4,744],[3478,-248],[3270,1673],[2131,38],[3325,3578],[477,83],[169,646],[848,407]],[[8031545,6939642],[-6580,-3600],[2200,-1000],[-2680,-2640],[2240,-720],[-1580,-2080],[760,-720],[-1920,-2460],[-740,300],[-3820,-1080],[-2180,180],[-760,-1000],[4140,-2040],[-480,-960],[1440,-600],[1380,-1420],[-2380,-1460],[1600,-2580],[300,-4000],[2300,-1980],[-18080,-2040],[-3700,60],[-380,140],[-500,3200],[-1080,-1040],[-1680,-660],[-1040,-2200],[-7980,-120],[-2760,4080],[-80,1320],[-6760,780],[-1360,560],[-480,1060],[-760,-260],[-1800,340],[-1000,-440],[-680,320],[-2420,-760],[-1940,0],[40,-820],[-1220,-640],[1560,-1460],[-1140,-1040],[-2000,40],[-360,-540],[-1740,-240],[-1460,-840],[-40,-480],[-880,-140],[-160,-880],[-1300,160],[-720,1400],[-700,-20],[-380,-2240],[-2200,-880]],[[8223016,6899607],[-837,-2007],[524,-137],[2539,2762],[2470,-1367],[1430,33],[8,-422],[1575,-1054],[-888,-707],[657,-403],[596,213],[1698,-1173],[-1335,-487],[1964,-1110],[-367,-226],[1791,-846],[1447,268],[1141,-749],[2408,421],[1867,-2860],[5475,700],[251,-516],[-695,-705],[28,-1012],[1447,-1395],[583,-1587],[-3325,-628],[-2077,-2082],[-1499,193],[-582,-1107],[-494,198],[-774,-973],[-1057,683],[-470,-185],[-1458,-1142],[902,-533],[-2031,-1196],[-2646,-3459],[-2911,-444],[-981,-701],[-4289,2959],[721,806],[-1087,391],[-1036,1384],[-2306,-719],[403,-417],[-238,-193],[-841,180],[-278,-602],[-698,-231],[-2866,585],[-3476,-687],[-1817,-1138],[-704,562],[-398,1432],[1109,672],[-539,1931],[2038,1334],[67,1379],[-810,547],[1102,408],[163,548],[-1897,2154],[-862,401],[-799,-385],[-1114,905],[959,784],[-1167,775],[1093,1043],[-1802,479],[786,120],[131,1990],[-983,13],[1480,729],[-735,512],[461,123],[-878,1462],[1383,683],[3359,-380],[787,847],[-702,195],[587,322],[1815,-503],[3273,374],[-927,1741],[1304,504],[3854,-277]],[[8460909,6805586],[-1288,-23],[-458,368],[-792,996],[-21,1380],[434,175],[1677,-707],[2183,710],[1925,-965],[1532,1209],[354,1364],[1824,907],[-268,1842],[-4190,1925],[-70,644],[613,1092],[1902,754],[946,1650],[353,864],[-199,2879],[1425,221],[346,792],[1912,630],[3977,761],[648,741],[25,1625],[1067,153],[-710,1781],[-808,487],[-34,1826],[750,507],[3214,48],[1969,2301],[1513,-232],[840,1123],[-1362,527],[1140,2776],[962,388],[-768,410],[-339,1246],[-1861,417]],[[8481272,6841178],[-1052,1788],[3388,527],[595,985],[1619,784],[-348,495],[1507,652],[-353,776],[1328,1589],[4474,1036],[2145,-254],[-312,660],[265,1170],[854,598],[1716,4218],[1170,199],[179,408],[770,-168],[1930,982],[6,3313],[-1124,364],[482,1530],[1564,2028],[2054,1275],[34,578],[-940,950],[736,233],[999,2657],[2545,2517],[366,1209],[1444,1409],[-118,537],[1407,161],[872,675],[1721,-317],[1191,327],[2151,-573],[2357,3767],[-579,933],[556,469],[-931,1495],[688,862],[-1194,353],[-1346,2132],[527,2557],[1149,1855],[2127,1982],[1605,-1078],[986,896],[-1611,1054],[2395,1377],[1451,-410],[1118,1448],[975,267],[1451,1383],[-84,890]],[[8528177,6898728],[4234,-636],[1032,882]],[[8184189,6896627],[3209,1783],[-29,1343],[1863,628],[624,1035],[2545,1323],[1149,124],[-842,885],[-2591,1287],[3060,-40],[124,1024],[3207,-1380],[1755,-370],[1382,302],[2183,-544],[-556,2711],[-1296,1441],[895,392],[-359,259],[137,1479],[2943,173],[1065,494],[2794,-1067],[1163,434],[733,962],[-1989,1567],[665,2558],[-1659,826],[-849,2873],[-1483,715],[-3645,508],[-186,394]],[[8200201,6920746],[711,915],[-2621,606],[-801,1725],[-2566,784],[-375,677],[-2867,657],[-78,1400],[-593,1183],[580,1211],[-544,1078],[1479,1129],[-168,1953],[534,682],[-1992,1674],[1094,998],[3455,9],[1503,870],[500,1288],[-548,1463],[1204,1402],[-696,49],[-63,383],[344,366],[571,-168],[426,666],[451,-144],[786,580],[2912,-581],[1197,1191],[2226,-754],[1878,587]],[[8208140,6944625],[3079,-3030],[3608,75],[913,-1083],[-383,-670],[685,39],[-542,-801],[293,-1068],[-1578,-385],[525,-838],[-5312,-2524],[751,-548],[-566,-470],[1483,-951],[967,-1310],[2063,-750],[1524,-1594],[2567,-857],[1695,-1141],[-145,-1110],[360,-561],[1712,-245],[934,-570],[96,-855],[1162,-522],[1183,273],[995,862],[5533,-621],[415,406],[1212,50],[2774,-715],[2276,-1670],[4466,-44],[4915,781],[3085,-1396],[3846,343],[1799,-605],[1351,58],[2083,-1433],[-1905,-561],[-1217,-2476],[2971,-364],[189,-772],[-1194,-1100],[-75,-1091],[1855,-2342],[1318,-337],[1172,-2403],[3161,816],[-14,812],[-1924,313],[146,563],[511,501],[2231,547],[2271,2309],[2979,-1150]],[[8272439,6912410],[3579,-2298],[-307,-1040],[-436,110],[-448,-575],[641,-354],[-980,-542],[2288,-3274],[3009,-909],[-748,-903],[585,-211],[1374,-1845],[-288,-1798],[1268,-996]],[[8324801,6839666],[-2473,1202],[-936,-629],[-6076,-1483],[-1705,-1530],[84,-2026],[-2879,907],[-2059,60],[-5757,2550],[-3648,-5352],[-1093,-20],[-2729,1109],[-2212,-660],[-8075,3970],[-6225,4960],[-1619,4439],[-3340,3852],[-923,-827],[-1653,-533],[-5537,1159],[-3158,-6391],[-1281,-161],[-3241,1023],[-5092,-2957],[-4525,-719],[-1386,-1419],[-2391,2324],[1870,3086],[3380,2645],[-3585,2718],[-4290,1372],[-3226,-333],[-2800,-4194],[-628,862],[-3852,-186],[-3202,-2400],[-2867,-519],[-512,-373],[-324,-1745],[-2562,-1088],[-4550,1447],[-362,532],[-6378,983],[137,-815],[1903,-1476],[-1088,-1212]],[[8211936,6841818],[-1970,1929],[-4576,2779],[-2742,6766],[55,2122],[856,3205],[2529,3061],[1274,3692],[-99,964],[-3875,406],[-674,819],[752,1493],[-2338,380],[975,927],[-543,610],[-5065,3323],[-3157,3362],[-2276,1598],[629,948],[2607,1286],[-394,3119],[-3403,3556],[-998,-357],[-1914,752],[-2720,3593],[-303,1590],[834,1315],[-1211,1571]],[[8031545,6939642],[3857,1281],[2635,-367],[1508,627],[558,-1054]],[[8040103,6940129],[92,-801],[1035,-556],[2095,-451],[3130,210],[2570,-390],[3859,-3239],[2620,-1042],[1155,-1521],[1935,-1284],[2405,-3734],[3907,-1472],[2940,-269],[1846,-1423],[612,-1991],[1734,-1671],[4166,628],[2616,-2169],[4842,-2184],[2234,-1951]],[[8085896,6914819],[5824,-1009],[1918,-911],[5462,120],[2135,549],[3506,-709]],[[8104741,6912859],[797,-3499],[-1243,-2056],[1088,-1257],[-747,-2712],[-582,-655],[762,-1131],[3845,-1013],[-1126,-2415],[-992,-694],[1102,-434],[-1797,-2138],[2044,-808],[277,459],[828,-783],[-2727,-675],[-2481,832],[69,-1860],[2568,-2502],[-143,-833],[-648,78],[-1919,-1056],[524,-962],[-1105,-67],[-484,-787],[1208,-608],[-1480,-573],[549,-675],[680,126],[1160,-2234],[-1773,-2835],[-70,-908],[817,-306]],[[8103742,6877878],[-667,-870],[-2038,-68],[-3225,-1996],[861,-926],[-206,-1031],[-983,-863],[-65,-769],[-3096,-108],[-197,365],[-752,-401],[-225,-2243],[427,-583],[-153,-947],[578,-621],[-1883,-673],[-70,812],[-841,856],[154,1628],[-478,919],[-2628,769],[-328,1264],[-818,618],[795,576],[33,804],[2424,698],[1547,1588],[-94,653],[2027,515],[-664,965],[890,616],[-831,1556],[-1641,1513],[-298,1345],[-2190,2369],[-1566,-1151],[971,-998],[-872,-286],[-391,509],[-1535,-414],[-290,466],[1127,1095],[-919,802],[-2098,-670],[-1225,550],[-674,-544],[-78,-1047],[-2133,-478],[113,609],[-1177,-240],[-1017,1027],[-1636,-939],[-1519,1321],[-1136,-913],[450,-824],[-2320,-1038],[-2577,1733],[-646,1012],[-2219,-2406],[390,-375],[-474,-616],[-2089,-1217],[-1862,657],[-506,-497],[-1416,722],[306,935],[-348,980],[-1194,265],[-1310,1394],[429,1063],[-3189,470],[-75,334],[-696,-1026],[-79,-1687],[-2112,-1519],[-3231,-403],[-386,332],[-3241,-1362],[-1953,456],[-981,-326],[-253,469],[-1733,-203],[-2140,571],[-52,-689],[-2097,345],[-862,984],[-1048,-317],[-932,-962]],[[8032606,6882162],[-44,308],[-2508,137],[-1077,-739],[-1120,-161],[418,-267],[-416,-857],[-1622,-59],[-1702,-923],[-2559,-76],[-2070,-1066],[-246,401],[1780,2176],[-214,1007],[1246,1010],[-1010,657],[-604,1259],[-3235,-2105],[-1929,-489],[194,-239],[-722,-628],[-3956,-1754],[-958,-733],[-179,-644],[-687,320],[-888,1343],[-1064,-18],[-205,403],[-954,-203],[-409,1068],[-8,-342],[-1293,-60],[177,-324],[-838,-403],[-1062,949],[-859,148],[-1873,2551],[-3591,-1408],[-822,845],[-1304,-693],[-573,685],[-2984,-770],[-3562,-1753],[320,-598],[-689,-299],[-668,840],[-827,-328],[-310,369],[-615,-210],[-498,605],[-846,-227],[-428,603],[-1913,927],[-826,1176]],[[8216807,6946692],[-553,-765],[-1342,-211],[-432,-1014],[-1004,-425],[-1278,478],[-4058,-130]],[[8200201,6920746],[-5512,503],[-5073,-930],[-972,-570],[-257,-1390],[-1227,-984],[-3564,-1683],[-3561,-858],[-2992,-146],[-5575,856],[-6721,-1350],[-2617,1099],[-1382,134],[-2458,-972],[-13651,-2382],[-7323,1082],[-4465,-121],[-8479,1496],[-4974,133],[-3931,-1105],[-2985,1135],[-2499,-1299],[-5242,-535]],[[8528177,6898728],[-1066,571],[14,787],[-1390,1897],[-17,2738],[-2060,645],[-786,710],[-1063,-168],[-2060,-3415],[-1746,-875],[-1,-644],[-532,-68],[-222,926],[-1041,384],[-565,838],[801,2299],[-1198,204],[-624,899],[-1245,-13],[112,1810],[548,1030],[-2688,491],[-264,482],[-900,210],[-178,601],[-2062,714],[-178,414],[-3698,-697],[-376,-2828],[-2530,-1297],[-266,-935],[-2270,-656],[-3041,503],[-696,1137],[-3182,164],[619,781],[142,1056],[-5219,160],[-1810,2594],[-2104,-220],[-61,-444],[-4331,306],[-948,729],[-4,987],[-1091,467],[76,353],[-2050,1686],[-5453,1878],[329,3550],[1135,4939],[1001,1311],[-1168,133],[-94,1609],[1233,2395],[-4971,1154],[-482,-748],[-1157,20],[-270,-838],[-6597,295],[-93,-582],[-1609,-201],[-9378,-69],[-4942,-1507],[-909,703],[-1,1244],[-2125,627],[-859,1011],[-3558,1629],[-4451,790],[-562,-1150],[-1152,791],[-688,-377],[-551,432]],[[8427554,6935080],[-1288,990],[-723,-69],[431,492],[-194,553],[-2540,2069],[367,730],[946,89],[317,1162],[1540,146],[354,796],[1682,1043],[-322,388],[370,248],[1970,-857],[938,479],[1023,-334],[-326,-744],[233,-683],[2156,300],[2610,-675],[1236,554],[-687,496],[35,562],[3624,2049],[206,-1767],[2409,-858],[879,499],[-158,-940],[2453,248],[1595,-992],[1366,456],[334,712],[1251,-90],[1534,-754],[268,183],[-589,730],[3086,-285],[936,443],[-752,892],[241,755],[1988,-959],[689,716],[47,1854],[2456,315],[-1292,906],[-1265,-158],[-452,936],[1647,-235],[219,455],[-2691,1620],[-992,1501],[1655,1276],[-553,283],[318,854],[-402,1315],[1324,578],[609,1244],[1151,236],[626,-255],[34,-706],[981,-310],[820,1369],[2209,-246],[-9,-414],[524,-108],[-127,475],[1889,146],[-821,513],[1767,632],[151,693],[3553,285],[75,516],[725,427],[2342,-1227],[2554,-419],[5272,-193],[2984,238],[407,433],[733,-1183],[965,682],[-782,114],[23,933],[963,-657],[2067,714],[-14,-1248],[1724,225],[-409,576],[544,116],[-71,607],[1184,-422],[308,707],[1073,126],[38,1067],[1727,490],[-395,664],[222,576],[348,96],[656,-821],[-30,985],[455,225],[1191,-915],[-657,-436],[903,-717],[-163,631],[1023,45],[-16,1000],[2444,-194],[2541,917],[1238,-733],[855,21],[712,1114],[1457,432],[-427,686],[658,-292],[1690,743],[2091,2405],[1951,712],[1217,1313],[1188,84],[-316,-1031],[2135,603],[1071,-1023],[1015,47],[309,405],[-353,1076],[2023,-311],[-69,1741],[1130,382],[299,-164],[-337,-564],[704,39],[54,561],[-690,383],[1518,722],[-831,151],[257,543],[1864,188],[-479,805],[-1136,299],[1900,-191],[3,562],[-962,438],[434,1020]],[[8527545,6976751],[1655,244],[-677,1048],[2090,502],[263,717]],[[8530876,6979262],[183,659],[2962,579],[2017,977],[890,-167],[1840,-1313],[3084,-83],[-799,-1609],[-1674,-744],[1167,-628],[1524,-1917],[3249,-746],[1801,57],[241,-1536],[-743,-1262],[828,-1169],[1595,-654],[166,-2881],[2118,-1361],[953,-2036],[1528,-1096],[1608,1495],[1904,163],[1282,-382],[8,551],[2449,-1099],[3213,1251],[1296,-541],[145,-310],[-626,-582],[1806,-154],[-246,-1181],[1837,-1687],[1300,-137],[1174,-948],[1430,-231],[-168,-1104],[-728,-354],[1364,-2228],[783,30],[1539,-1430],[-1006,-341],[712,-647],[-287,-1174],[681,-740],[-707,-294],[-196,-573],[1374,-363],[1584,191],[1518,-987],[3624,-428],[3397,1807],[2439,498],[505,471],[2105,68],[788,-967],[794,-146],[630,293],[-744,548],[141,408],[1863,-487],[1314,493],[299,-436],[-510,-754],[431,-351],[981,1161],[1048,-109],[536,-821],[-361,-1282],[842,-1566],[1127,333],[1360,-892],[-266,-564],[640,-950],[-394,-153],[849,-629],[1201,338],[-106,-1848],[-742,-1149],[-813,-274],[106,-1003],[-2955,-2135],[791,-580],[-332,-403],[1107,101],[1485,-781],[250,268],[1023,-1333],[1330,357],[-204,-908],[437,-277]],[[8211936,6841818],[-118,-1859],[-1607,-1879],[271,-2259],[1142,-2008],[213,-1801],[-663,-2492],[-2658,-3022],[-661,-1858]],[[8207855,6824640],[-1916,121],[-4505,-857],[1455,-1181],[-351,-461],[-515,-110],[-493,-1026],[-2644,-1733],[-4054,-1724],[-310,-298],[561,-1476],[-4841,-157],[-941,-740],[-2715,-572],[1872,-2927],[-624,-230],[214,-232],[-2041,-539],[-2471,-1886],[-4563,-967],[-280,560],[-524,-65],[303,1010],[-636,111],[192,831],[-726,823],[1062,387],[-1082,579],[-345,1705],[-1470,-52],[-1585,1053],[-1288,256],[-1590,2527],[-5275,-2080],[860,-1812],[-1196,256],[-1055,-365],[-1204,384],[-1313,-704],[441,-284],[-5030,1396],[783,1552],[-865,1190],[376,945],[-1306,1415],[-541,-3369],[-654,44],[-170,1526],[-874,-67],[-423,629],[-1040,-553],[-439,-610],[362,-264],[-589,-231],[-1784,929],[-2682,665],[-1041,712],[37,1540],[-704,456],[-3847,-1975],[-444,-708],[-836,-167],[-50,-462],[-4063,-617]],[[8136438,6816741],[-1267,3485],[648,2466],[-750,2670],[912,291],[-1687,592],[2338,1397],[-2105,3592],[185,496],[-1940,1815]],[[8132772,6833545],[3174,2546],[633,2757],[1535,378],[1071,1082],[2330,620],[-295,490],[-1990,-532],[-477,953],[-2158,1936],[-933,3058],[1222,864],[1893,566],[-1100,1228],[-35,1803],[-1101,4008],[937,244],[-412,739],[1007,-23],[-668,795],[374,3231],[-771,1093],[-2031,-187],[-2304,1646],[-276,1323],[-1318,1171],[-1500,-66],[-3676,-1397],[-1256,753],[-1798,2266],[-2073,-141],[-711,2708],[1861,1343],[-1784,183],[-1219,1371]],[[8118923,6872354],[-200,568],[1965,1114],[3440,739],[-747,701],[-84,736],[1231,1779],[1710,1092],[133,936],[-548,877],[1478,908],[-432,1569],[2220,737],[1350,-1178],[2050,839],[1470,-291],[852,883],[-293,251],[317,1053],[-639,882],[1065,51],[1912,-1263],[2261,-588],[34,-1486],[622,-905],[3041,-1093],[707,-1116],[2675,-1323],[1425,743],[473,952],[1208,-580],[3467,799],[-2644,1810],[73,576],[1819,1606],[809,211],[1447,-1125],[2715,2069],[800,1622],[885,116],[319,521],[1559,-581],[1951,-1619],[649,621],[64,1021],[2422,1129],[2116,-1343],[1671,-237],[-1376,1261],[26,617],[-1011,225],[-2061,1629],[-613,843],[236,834],[-1094,1254],[352,586],[3378,210],[1212,-514],[1443,1765],[1326,-192],[1421,706],[4054,-982],[551,678],[4194,-99],[2410,669]],[[8481272,6841178],[-1811,-486],[-184,733],[-509,-110],[-727,-334],[-210,-730],[-602,38],[462,-580],[-2048,-966],[-2796,76],[-634,388],[-1558,-2445],[953,-1684],[-2478,-168],[-403,-814],[-1249,501],[-455,-550],[-317,335],[-1032,-445],[-666,171],[-1089,-1035],[-672,-5],[-732,780],[-2825,709],[-2014,-1333],[191,785],[610,65],[-117,585],[1218,127],[-402,1225],[-1323,-194],[-1069,757],[-5939,322],[-10038,2975],[-712,-274],[-1467,1636],[752,1412],[-838,2262],[6322,2675],[-368,1697],[1571,710],[-655,682],[-132,1158],[-549,199],[667,1962],[-3227,-397],[-1385,27],[-1411,604],[-1023,-280],[-1991,1459],[-8504,1003],[-6469,3408],[498,-1528],[-1404,-321],[-3163,3495],[-568,-72],[-471,721],[-1751,39]],[[8398128,6904812],[592,-215],[351,557],[794,-566],[899,108],[14,-776],[497,-431],[1707,-252],[299,640],[-1966,877],[-783,1688],[4195,-460],[739,799],[-1402,-96],[-402,1288],[401,736],[1572,-1226],[1505,822],[1664,-3],[-68,1081],[1648,1190],[4525,325],[507,792],[-503,1004],[661,438],[-597,743],[1116,751],[1761,-25],[1070,-1064],[811,1316],[-221,269],[1129,1187],[-494,266],[718,103],[447,1106],[634,172],[-82,966],[1558,2032],[-706,1355],[-1540,1190],[260,238],[-914,333],[945,772],[1017,-119],[-30,367],[1116,233],[99,2606],[1343,1233],[2475,469],[119,1118],[-3163,-17],[370,767],[1774,747],[965,2834]],[[8527545,6976751],[-966,296],[-1124,-506],[-778,262],[-722,-709],[-158,918],[-778,639],[-2205,-976],[-3310,1495],[-362,-615],[-2344,-890],[-4648,63],[-1521,-848],[-594,112],[535,-623],[-413,-286],[-2808,868],[-83,-732],[-1109,56],[346,541],[-775,-226],[441,-775],[-394,-279],[-320,656],[-706,-249],[88,-432],[-1102,407],[46,-446],[-858,1049],[-1949,-315],[-61,-2778],[-1107,-129],[-2598,854],[-3445,-340],[-1939,989],[-2193,116],[-1097,745],[294,839],[-921,23],[-198,401],[229,651],[-769,659],[-1458,776],[-1505,-182],[-397,307],[273,726],[-396,1850],[-361,-40],[-751,1850],[-2179,1459],[-188,583],[317,276],[-1142,1026],[304,415],[-213,1858],[-651,560],[-63,1134],[-1020,-157],[-968,587],[-1610,-911],[-1227,99],[-459,619],[-1908,-318],[-103,532],[-1596,919],[-946,1683],[291,728],[-322,305],[-1842,880],[-848,-27],[-3004,1682],[-752,-41],[-1082,1036],[-1757,-653],[-109,-1538],[-518,-409],[-1586,460],[-2087,-566],[-5836,352],[-530,-548],[1086,-187],[-1324,-328],[704,-540],[-1064,-645],[604,-648],[-1339,-609],[558,-77],[-246,-362],[-3926,388],[-2744,1354],[-619,-65],[65,-488],[-1222,331],[-474,-592],[-734,190],[-341,-617],[-1766,-297],[-825,-609],[-1879,332],[-1941,-1380],[-792,-1250],[-1610,-420],[-1626,354],[-691,590],[387,984],[-813,727],[-2379,834],[-1280,-374],[-12,400],[-3812,610],[-2484,-599],[-879,-850],[-538,665],[-1997,-277],[-34,1235],[-1492,70],[89,827],[-709,-158],[-1258,1812],[-5444,-737],[-1258,1360],[-814,222],[336,1353],[-1264,-732],[-233,222],[414,390],[-343,249],[-3648,-824],[-6572,-450],[70,-345],[-2119,385],[-3248,-941],[-2705,25],[-1015,-896],[-342,308],[-1688,-461],[-730,-711],[-1665,-117],[-1305,-675],[-4027,845],[-894,-1638],[-1208,265],[-593,695],[-1293,-312],[-453,-715],[75,-742],[766,-749],[-543,-2041],[304,-245],[-1309,-179],[-638,-1193],[-2424,-1169]],[[8361773,6985326],[531,-419],[10,-721],[-2398,-794],[-1114,-1461],[-1851,-1159],[-167,-792],[623,-649],[-758,-1614],[-1029,-539],[910,-1291],[-436,-679],[-2310,-1162],[164,-414],[-1825,-1494],[646,-531],[-1776,-1406],[158,-301],[-2284,-1077],[47,-1126],[-756,66],[-242,-1557],[-1816,13],[224,-790],[-2494,-306],[-3488,1710],[-1472,84],[-723,-284],[738,-557],[-1050,-820],[-947,-429],[-1154,281],[212,-1087],[-1593,-286],[-5675,585],[-129,-649],[764,-431],[-538,-779],[-24,-1022],[-3177,-1566],[-1219,-1274],[-2027,-520],[-208,-322],[1087,-491],[-1712,-508],[-964,-1065]],[[8320531,6955693],[-737,-45],[-124,587],[-1508,396],[-3618,-866],[-334,-620],[-1393,382],[-1101,-1396],[-1193,-56],[-1471,-1436],[1,-556],[-2883,-209],[-731,-490],[-284,476],[425,735],[1217,1043],[-771,344],[-783,1578],[-1401,-194],[-1682,709],[-792,-205],[-509,893],[-983,-1561],[-1749,98],[211,345],[-825,185],[-730,-182],[-1124,-1232],[-828,-128],[-1202,1117],[675,328],[-96,515],[1692,1052],[-635,1085],[-1188,-206],[-595,866],[-1439,453],[-616,818],[-1456,266],[-1133,-140],[-1399,-1344],[-2798,294],[-1792,1518],[-475,1925],[-2533,10],[-1407,1102],[-4992,-3109],[-3446,-1362],[-406,476],[-1477,-637],[-252,-264],[434,-993],[-2470,-1802],[401,-211],[441,-1598],[-2076,-1551],[356,-206],[102,-1288],[-311,-1584],[-952,-410],[291,-510],[-1888,-770],[-110,-808],[-539,-89],[-972,949],[-42,408],[541,114],[-259,347],[-1196,-6],[-1704,-1204],[-1628,-19],[-951,-477],[-1259,776],[-1909,-397],[-1213,279],[-5495,-243],[-1629,-593],[-758,-841],[-1969,-158],[-892,-1385],[-889,-480],[-2724,1066],[-3154,-317],[-3041,573],[-1489,716],[-2771,-849],[-2259,728],[-1992,-830],[-598,-749],[-1283,928],[-1301,-200],[-1897,1325]],[[8320531,6955693],[998,-72],[490,-1268],[2092,-97],[552,-1018]],[[8324663,6953238],[-1442,-817],[-39,-816],[-579,-509],[-2518,100],[191,-765],[-917,-914],[-3468,-392],[-2445,-971],[-462,326],[-802,-580],[468,-254],[-39,-907],[1411,-267],[722,-1037],[2409,-1190],[-988,-151],[524,-750],[-303,-273],[294,-1728],[276,-666],[1074,-232],[528,-583],[-2851,-519],[-744,279],[-577,-786],[-996,-96],[-476,-919],[1071,-900],[-2219,-857],[371,-2128],[-2693,-617],[-918,-1922],[-1134,-109],[-494,-747],[-2042,80],[-1617,1343],[-4509,-206],[-2468,-560],[30,-1415],[376,-145],[-424,-280],[2136,-843],[1081,557],[1412,-1068],[-575,-67],[-623,-1378],[-731,-204],[-1043,126],[-1250,990],[-1096,93],[-2487,1826],[-935,-180],[-31,-640],[-816,-539],[-2,-291],[640,43],[-158,-1909],[-3805,-2960],[-1022,-1562],[183,-579],[-908,-299],[-2336,450],[-225,-896],[-1634,-108],[135,-786],[-427,-232],[-683,301],[-359,1055],[-2106,-760],[1048,-2327],[-401,-1956],[-940,-882],[-1734,797],[-4113,-2720]],[[8118923,6872354],[-1937,521],[-2207,-597],[-2282,550],[-870,-547],[-152,1409],[-658,617],[-1937,881],[-813,-90],[2311,769],[-154,940],[-1494,940],[-1881,114],[-990,-683],[-2117,700]],[[8392502,6904358],[-6223,3552],[-2157,-314],[-1095,746],[-401,-816],[-2350,-58],[-4661,1273],[-1357,1295],[-1139,31],[-890,628],[2705,2226],[-6721,3705],[-897,1457],[-1708,1483],[-111,1287],[988,852],[156,1049],[-989,2465],[-860,554],[-3031,552],[-1447,1576],[-163,888],[1470,991],[1058,130],[754,-591],[1132,410],[521,-214],[-347,1418],[2366,852],[-660,1244],[-1246,-3],[-4720,2721],[976,562],[991,1761],[805,70],[560,2666],[597,491],[188,1698],[-924,714],[-483,1057],[2137,321],[241,523],[-782,744],[168,557],[-418,721],[-1006,848],[235,1682],[-577,511],[-252,1211],[-746,133],[-651,1139],[-1035,464],[270,355],[-3843,-104],[-779,425],[-2127,-417],[842,-1277],[-1954,-788],[-153,-877],[-1198,-796],[20,-1917],[-382,-177],[-1373,1192],[-1907,634],[-608,1392],[-1706,-435],[-1497,413],[-960,-1507],[613,-441],[-420,-578],[-536,-307],[-1441,170],[-1125,-767],[-865,456],[-1873,-140],[-1722,453],[-433,614],[281,501],[-3249,782],[-573,1932],[-1320,43],[-1353,822],[-1152,116],[-2557,-685],[-760,531]],[[8106509,6718017],[-1480,-89],[-2483,-1345],[-317,-868],[-673,-61],[-929,841],[-28,739],[-1941,851],[-615,1731],[-1926,-499],[-3001,1339],[-1819,-561],[-1645,1688],[-3602,299],[-1905,723],[-1879,-363],[-1771,1264]],[[8080495,6723706],[1393,185],[399,1683],[1926,704],[593,-680],[-206,-870],[1029,1025],[2470,-371],[291,231],[-432,443],[823,687],[-873,1428],[788,501],[-1361,774],[425,1047],[-3003,931],[-1101,-69],[-740,1157],[1104,210],[-223,529],[-1434,-111],[-226,381],[-597,-130],[-301,696],[-577,-119],[603,-1382],[-1453,-216],[-250,1942],[-939,1589],[-348,1868],[-470,-49],[2837,302],[-25,1412],[360,209],[-1816,1154],[-995,2608],[280,402],[2480,471],[-80,702],[1462,197],[-48,994],[716,97],[-25,1534],[429,266],[-1563,1013],[2244,779],[-732,951],[372,330],[-258,1150],[557,2571],[1821,2176],[-218,1385],[1475,349],[1005,985],[-550,1111],[-659,121],[348,669],[1264,532],[1821,-2702],[791,-413],[1861,121],[835,1343],[-92,571],[1012,474],[878,-763],[939,300],[285,-1121],[660,175],[1504,-544],[1020,932],[544,-228],[823,609],[1027,-516],[662,888],[1507,-343],[625,45],[648,746],[1711,-233],[1190,1460],[-686,1530],[1007,1916],[-273,1100],[1387,1752],[516,-281],[2219,715],[2597,96],[55,-711],[1239,-453],[942,375],[1938,-822],[953,301]],[[8120631,6768509],[535,-374],[119,271],[1619,-317],[317,718],[2207,341],[1311,-1852],[837,-252],[958,1031],[-756,-252],[-938,348],[301,726],[-781,1160],[361,714],[1896,394],[577,-132],[69,-426],[1304,30],[100,907],[328,-651],[684,-26],[1658,1320],[1906,-107],[313,2471],[-1359,748],[-307,3379],[3495,814],[1666,-331],[612,533],[2474,-614],[4596,1559],[1691,-889],[691,47],[669,-743],[279,-479],[-528,-605],[-66,-1533],[896,-799],[85,-706],[3497,-1005],[308,-1389],[-1619,-801],[233,-3480],[2261,-670],[1650,456],[731,-1427],[-576,-113],[-475,-807],[-795,-2273],[-878,-788],[-3317,-843],[-212,-263],[543,-707],[1525,-408],[6438,2924],[-45,899],[2090,49],[-452,750],[1990,853],[49,1705],[-522,1329],[342,80],[572,-676],[2398,-319],[45,-370],[1002,-307],[-425,-1037],[355,-279],[1208,-228],[107,933],[1080,-472],[-365,-2950],[-1039,-998],[436,-596],[2210,-907],[1369,420],[249,-684],[-590,-451],[670,-781],[-151,-492],[1087,-316],[1199,-1433],[1991,895],[772,-1146],[2112,-1012],[1538,-1717],[2137,-1221],[906,-1490],[522,247],[-326,536],[373,212],[2785,-1619],[884,198],[1698,-1071],[2455,488],[862,-566],[2229,3]],[[8195571,6749797],[-471,-510],[-2763,-932],[-1353,-2694],[-2364,-2227],[998,-1652],[2125,244],[1070,-736],[1329,444],[2104,-386],[2852,1735],[951,-693],[-377,-497],[2500,-895],[-3311,-4133],[528,-393],[-1549,-1547],[3,-348],[1553,-320],[1541,-1034],[-1032,-241],[-133,694],[-626,-83],[-1023,-784],[-2523,-841],[1876,-1608]],[[8197476,6730360],[-1369,-1105],[529,-1196],[-366,-1207],[-1702,-129],[-1934,992],[-1232,48],[24,457],[-1099,652],[-3026,663],[-1494,1191],[-2858,-333],[-641,-413],[-1033,642],[293,-2073],[-2117,-750],[1417,-1450],[-1733,-635],[-665,848],[-349,-333],[-417,-1909],[-880,-71],[873,-1389],[-2276,-568],[294,-583],[-914,-703],[-2160,-713],[198,-1348],[-1565,339],[-474,-954],[-2229,-90],[-1095,-566],[73,-513],[-1425,359],[-646,813],[-1087,61],[-847,-1944],[-2,-994],[-2573,402],[-1148,-916],[409,-245],[166,-1244],[-363,-826],[-1919,450],[-2047,-188],[-920,492],[195,1030],[-273,-232],[-530,890],[-2793,1136],[274,-644],[-1076,15],[-1768,-1953],[-647,722],[-3269,608],[-2324,-480],[-1543,551],[-1721,6],[-1310,1774],[-2523,248],[-1393,616],[-2271,-1159],[-1801,1130],[-2645,219],[-1713,-1873],[-2475,-637],[-5572,1326],[-3017,1778],[-2295,-633],[-2405,340],[-2021,-641],[-1722,499]],[[7926545,6825862],[1457,-1249],[2951,-321],[621,553],[1454,-179],[877,829],[3014,273],[1748,820],[5815,-385],[1016,-1330],[1700,-324],[1073,-1059],[1109,118],[738,-615],[310,-1065],[-624,-34],[-428,-793],[-39,-1779],[-2692,-637],[-81,-1965],[1779,-9],[-1133,-2373],[2164,-1257],[968,-1077],[-287,-629],[1000,-1027],[1368,795]],[[7952423,6811143],[902,-1020],[-1125,-775],[1279,-617],[4728,-414],[-817,-1821],[489,-539],[-686,-574],[131,-613],[-1664,34],[-726,590],[-1062,-1080],[647,-2018],[2076,-613],[1240,-1445],[2047,-219],[2377,-2535],[432,193],[989,-902],[-48,-1243],[1023,-358],[1524,272],[1031,-1255],[-105,-1637],[1483,-476],[-804,-1204],[141,-412],[744,-104],[-328,-681],[-632,-224],[4539,-1740],[1147,-1004],[1740,-136]],[[8044778,6737776],[1344,-699],[666,911],[861,-181],[-562,-1283],[-896,-448],[481,-533],[1573,329],[739,935],[26,512],[-915,641],[399,505],[844,-72],[301,-1080],[1150,-926],[559,290],[305,1343],[1027,-129],[35,-725],[-637,-751],[765,-576],[-1315,-49],[-255,-446],[1085,-328],[1630,482],[413,-644],[-682,-316],[-2403,218],[-627,-562],[-816,822],[-607,-555],[458,-1096],[810,-340],[2143,664],[1260,-135],[-99,-898],[721,-642],[1857,911],[155,-987],[2357,-132],[170,385],[-989,1172],[1370,596],[3302,-800],[3855,-265],[1625,-601],[2682,452],[1288,-213],[4740,-2716],[1157,-1093],[2020,-3175],[347,-1842]],[[8044778,6737776],[160,490],[891,316],[-13,601],[-2128,-209],[-2598,1164],[1677,852],[1833,239],[200,814],[-2591,268],[-1450,-380],[496,651],[-174,996],[1409,691],[-185,405],[-3834,310],[122,539],[1263,-473],[618,315],[-1065,154],[-96,1075],[-818,379],[-3034,-246],[565,532],[1115,-67],[580,1156],[973,348],[-2408,151],[907,922],[-391,566],[-2866,-763],[-1008,244],[594,973],[-724,1019],[1154,414],[-892,1223],[262,565],[-2308,818],[153,1123],[-1884,229],[-1361,-410],[-260,1085],[-1122,-283],[-1081,1015],[-1062,286],[-853,-352],[-1246,777],[-286,841],[-1295,22],[-4703,2069],[-3352,165],[57,1753],[-2060,-267],[-2202,1735],[-1764,482],[-1069,1238],[-1710,632],[95,1473],[-939,1139],[-121,1402]],[[8002949,6770982],[2,451],[891,-98],[1172,-1154],[3861,434],[-137,-1430],[466,-18],[-15,-1116],[1721,414],[721,886],[1406,96],[787,1031],[2137,-389],[657,-637],[1347,419],[1402,672],[-323,1297],[876,987],[1220,91],[-508,2602],[-922,690],[252,681],[-288,673],[-1275,960],[621,2006],[1723,74],[70,-876],[1376,-637],[953,323],[208,1150],[643,438],[907,-79],[1761,-541],[86,-817],[1164,-83],[1323,221],[241,1966],[3856,501],[777,-322],[709,3626],[-638,858],[173,1189],[1084,-139],[347,895],[999,134],[1187,1679],[-1123,9891],[642,2398],[-372,1425],[394,2300],[3532,1557],[551,2020],[669,2637],[9242,-221],[3598,1670],[2163,229]],[[8057265,6813996],[2640,-287],[1948,511],[2690,13],[4189,1844],[13356,4048],[6227,2842],[5886,1317],[6563,3078],[2411,-623],[1081,174],[2124,1422],[214,1318],[-486,863],[9987,2798],[5919,2583],[8073,-1536],[863,518],[1822,-1334]],[[8136438,6816741],[-1122,-10],[-1339,-781],[-1223,172],[-815,-513],[599,-2195],[-1584,-236],[-595,664],[-926,-184],[210,-408],[-556,-100],[-6,-637],[-2353,-568],[1590,-2606],[1150,468],[528,-623],[-898,-222],[301,-671],[-923,72],[130,-562],[-450,-123],[313,-1052],[-1902,-641],[-513,-1091],[-555,-212],[592,-820],[-1821,-812],[-100,-1126],[-1759,-881],[1636,-2642],[-256,-1187],[-587,-124],[-676,-1741],[-881,-764],[-1329,-306],[-1208,728],[78,-2133],[-604,-256],[500,-3273],[-657,-265],[936,-702],[1133,-3258],[1640,-2502],[-377,-262],[238,-1128],[-1759,-128],[48,-572],[-504,-227],[-560,451],[-234,-606],[-1651,-452],[178,-381],[-754,171],[-1040,-547],[1017,-1708],[1707,643],[245,-452],[1848,790],[1304,-2791],[1655,150],[589,-3723],[-1255,-1109],[-54,-1163],[-2146,-1065]],[[8197476,6730360],[646,-962],[4069,653],[-364,968],[1056,-545],[1435,566]],[[8460909,6805586],[-98,-597],[-1317,-922],[-2507,-893],[-643,-2069],[-2875,655],[-1563,944],[-1244,-760],[-2321,135],[-1587,-1399],[-1297,-2677],[1965,-800],[-3112,-3851],[-933,66],[-610,-425],[201,-570],[-1582,-3305],[1387,-2550],[2204,-31],[2143,-2546],[-459,-117],[-137,-930],[-2204,-2506],[649,-847],[-1312,-347],[-5775,1034],[-622,-246],[-277,-926],[-1002,138],[-979,-3242],[295,-2291],[-916,-875],[-1419,-355],[257,-514],[-561,-1204],[738,-1432],[-609,-384],[-2284,-271],[-616,712],[-2992,-302],[-1234,-3905],[-874,-24],[-1462,-1031],[-868,181],[-517,-1112],[-2924,514],[-1176,1860],[-3465,-700],[-3781,531],[-584,1435],[-2155,-288],[-294,-1443],[-3158,959],[-1721,1598],[-8414,-1424],[-1365,278]],[[8392903,6766515],[-2691,1446],[1446,5097],[-2442,4292],[-4509,-339],[-1099,-2959],[-5898,334],[-169,-316],[-5019,1403],[724,584],[-3011,2007],[1139,1388],[2256,307],[-61,4422],[2418,465],[-1189,1948],[650,312],[-232,759],[343,1467],[1236,2438],[-392,963],[-3131,2795],[-502,5503],[237,1266],[-757,117],[704,3192],[-94,1425],[1731,87],[-827,1637],[-267,2293],[1424,4038],[-3312,1644],[-5938,-272],[-1039,1368],[-3963,2504],[-2908,-855]],[[8000821,6773966],[1116,393],[-393,-823],[1145,-297],[-128,-684],[781,-42],[-677,-956],[284,-575]],[[8207855,6824640],[134,-3955],[890,-880],[1816,-818],[-388,-198],[680,-1349],[1452,-2095],[698,80],[568,-2473],[1830,-2257],[412,-1870],[-271,-745],[-3552,-3731],[-1200,-581],[-45,483],[-1167,-365],[-2640,-1215],[-3467,-107],[-2292,-2598],[408,-1450],[3161,-3642],[63,-4072],[2122,-2778],[487,-1633],[182,-1071],[-400,-1440],[-3120,-3856],[-370,-1544],[1408,-6164],[1993,-1882],[235,-1426],[-1025,-3995],[-1940,-137],[-1695,1106],[-741,-93],[-527,-442],[1452,-1982],[-186,-770],[-795,-589],[-1287,413],[-3109,-2675],[-79,-386],[1012,-462],[3959,2139],[-632,-1731],[509,-1197],[-1608,-25],[-282,-828],[-807,-104],[-467,-1609],[86,-2190],[-796,-162],[-2089,-2931],[810,-559],[-1674,-2]],[[8385870,6755063],[-1106,-299],[-965,-1361],[-1910,697],[-1044,-219],[-1036,-1968],[-1059,-340],[-2338,1918],[-1730,428],[-4128,2556],[-5079,1443],[-946,-917],[451,-281],[-118,-707],[-3606,-2802],[-3279,235],[-2886,1218],[-317,-487],[-1316,534],[-1268,-497],[-1284,1676],[-4298,-1951],[-344,630],[-1235,-423],[-3095,-2551]],[[8341934,6751595],[-1097,-1094],[-537,407],[201,659],[-334,338],[-1504,-603],[-335,527],[-1950,639],[-230,848],[-2621,1611],[-4453,-1582],[-3043,1842],[-86,1207],[-1020,253],[-3206,-3359],[-568,425],[-2503,-123],[-1061,2664],[-663,345],[-8064,-58],[-2015,-1216],[-4164,-1267],[-2016,-158],[-3538,-2200],[-3714,1675],[-2219,335],[-1765,1790],[-2291,580],[-25,440],[-1958,1195]],[[8285155,6757715],[-1154,2494],[-4835,5124],[5086,4164],[-2637,2565],[-672,1556],[4088,1201],[2544,297],[2095,-1194],[7590,3894],[3806,-1589],[2388,1303],[383,1473],[945,779],[405,1076],[-15,539],[-1602,1966],[1726,1564],[166,764],[-596,1261],[-4731,3070],[-3856,-503],[-2937,2591],[5973,2816],[5239,1830],[5137,-3013],[1923,2015],[3178,2317],[-503,1174],[466,1954],[-343,924],[-999,488],[456,1758],[2282,2519],[305,1528],[-550,842],[-3644,2337],[5541,5376],[3654,2589]],[[8392903,6766515],[-2669,-2529],[1295,-4618],[-3445,293],[-167,-1096],[836,-263],[-1169,-635],[-742,-2059],[-972,-545]],[[8057265,6813996],[-182,678],[-3652,2435],[-2146,1313],[-654,1929],[-2727,1477],[13,1685],[923,1200],[-416,916],[-1346,898],[933,624],[-489,1110],[-1696,489],[-9,763],[-2048,1426],[-2834,-378],[-2518,359],[-504,1044],[1588,1446],[-337,957],[1134,222],[-887,1827],[-1081,593],[207,501],[-401,468],[-1777,784],[-378,712],[-728,-713],[-1557,-258],[-4003,408],[-105,1466],[-1613,156],[-5151,3263]],[[8022824,6843796],[159,1672],[3102,150],[3746,1264],[855,-76],[613,-723],[599,813],[2004,-1328],[988,12],[562,851],[1446,710],[-458,2914],[1086,250],[-1261,483],[-685,1139],[-800,3204],[1491,1540],[-145,1450],[592,1459],[-705,697],[276,18],[-60,1983],[-945,3389],[849,1271],[603,-536],[517,640],[-46,1073],[-573,735],[1188,951],[1667,879],[3118,-20],[2298,1154],[-2681,1602],[-982,-159],[-3175,1152],[-836,893],[-675,-164],[-2343,1899],[1971,1110],[-1793,866],[-1288,2919],[-497,230]],[[8022824,6843796],[55,-2346],[-284,-142],[-1602,700],[-1151,-636],[-730,1669],[-1638,-364],[-561,454],[-1402,-689],[907,-1511],[-82,-944],[1042,-1547],[-376,430],[-517,-743],[-2640,-1148],[270,-1028],[650,-402],[-272,-313],[-570,296],[-686,-447],[-5556,-10],[-593,1073],[-2080,267],[-1818,-527],[-1007,301],[-2098,-244],[-936,1044],[-1373,-735],[-660,95],[-68,-2413],[-3057,-269],[44,-1547],[-954,-678],[-4106,774],[-3526,-422],[-1467,866],[-1933,-431],[-1564,-1227],[-2066,468],[-2751,-2892],[-1159,-649],[-1195,-1493],[326,-408],[-1533,-321],[59,-1179],[-581,-93],[-33,-1087],[-417,-35],[-139,-527],[-1818,292],[-3648,-696],[446,-671],[-6,-2055],[-1633,-1009],[-4785,-1850],[-4743,1071],[-1337,-404],[-289,-466],[-1601,-36],[817,-1096],[1521,696],[2090,-332],[-2129,-1028],[-131,-432],[1008,-1622],[-1251,-663],[-1084,-1342]],[[7926545,6825862],[2240,680],[540,940],[680,100],[1700,1860],[1620,180],[1880,3420],[840,200],[1460,-720],[1680,1140],[800,20],[-340,920],[760,540],[1420,340],[1260,-220],[-40,2120],[1400,2940],[860,-420],[20,-880],[380,-240],[1980,440],[1960,-680],[240,840],[680,520],[1640,-340],[540,-780],[3940,640],[1380,-1160],[1802,26],[398,1014],[3080,-940],[1100,600],[2240,80],[-1980,940],[-980,1220],[-500,-140],[-240,600],[-1160,520],[-1560,-980],[-940,720],[520,460],[-380,140],[680,360],[5960,1040],[1400,680],[0,520],[-1100,480],[-1360,420],[-840,-180],[-480,640],[-980,-180],[-200,460],[420,740],[-1160,940],[1140,1020],[260,-360],[700,100],[-220,660],[1800,80],[-100,1360],[3000,400],[-60,1000],[-1220,1200],[-6220,-700],[-500,960],[1340,1040],[-800,2480],[-2480,-280],[-1000,1060],[20,1600],[300,-360],[1360,240],[180,2020],[440,380],[-100,1480],[-1140,180],[160,260],[1680,-240],[-220,280],[2240,180],[1080,740],[-120,1400],[1100,380],[-2500,5360],[-1700,580],[-300,680],[-1040,600]],[[8285155,6757715],[-1555,-819],[-2102,1031],[-2994,-2082],[-6845,775],[-270,-1068],[-3387,-1862],[-983,405],[-1429,-964],[699,-475],[-135,-376],[1897,-1264],[-6264,-2566],[211,-1363],[-2737,-1490],[-2373,-2103],[-3525,-991],[-1601,1635],[-8254,-3762],[2108,-2299],[-618,-375],[-1119,896],[-4869,-170],[-393,427],[-2613,-48],[-703,-68],[535,-549],[-5718,342],[-55,1187],[-1339,2910],[-2921,291],[-3891,-3995],[1387,-3649],[-4687,111],[-2686,-595],[-794,-1250],[1097,-2289],[-1415,57],[-674,833],[-2594,-634],[-5601,940],[-1627,-1409]],[[7975135,6786573],[655,-49],[591,-702],[664,-421],[872,337],[609,-681],[1376,309],[1882,-510],[196,-553],[-797,-842],[1598,273],[4330,-5636],[448,18],[467,863],[711,54],[541,-298],[169,-1165],[1279,182],[767,-976],[801,701],[723,-679],[1190,733],[1130,-60],[265,-751],[775,-92],[402,-608],[847,227],[556,-567],[526,742],[478,-180],[-298,-734],[1539,-516],[394,-1026]]]}